three/__init__.py
three/__version__.py
three/three.py
love_three-1.1.0.dist-info/LICENSE.txt
love_three-1.1.0.dist-info/METADATA
love_three-1.1.0.dist-info/WHEEL
love_three-1.1.0.dist-info/top_level.txt
love_three-1.1.0.dist-info/RECORD
