Metadata-Version: 2.1
Name: love-three
Version: 1.1.0
Summary: A package for all those who love the number 3.
Home-page: https://github.com/JasonTurley/three
Author: Jason Turley
Author-email: jasonturley0@gmail.com
License: MIT
Platform: UNKNOWN
Classifier: License :: OSI Approved :: MIT License
Classifier: Programming Language :: Python
Classifier: Programming Language :: Python :: 3
Classifier: Programming Language :: Python :: 3.6
Classifier: Programming Language :: Python :: Implementation :: CPython
Requires-Python: >=3.6.0
